kuzu_memory/__init__.py
kuzu_memory/__version__.py
kuzu_memory/async_memory/__init__.py
kuzu_memory/async_memory/async_cli.py
kuzu_memory/async_memory/background_learner.py
kuzu_memory/async_memory/queue_manager.py
kuzu_memory/async_memory/status_reporter.py
kuzu_memory/caching/__init__.py
kuzu_memory/caching/embeddings_cache.py
kuzu_memory/caching/lru_cache.py
kuzu_memory/caching/memory_cache.py
kuzu_memory/cli/__init__.py
kuzu_memory/cli/async_utils.py
kuzu_memory/cli/auggie_cli.py
kuzu_memory/cli/cli_utils.py
kuzu_memory/cli/commands.py
kuzu_memory/cli/doctor_commands.py
kuzu_memory/cli/enums.py
kuzu_memory/cli/git_commands.py
kuzu_memory/cli/help_commands.py
kuzu_memory/cli/hooks_commands.py
kuzu_memory/cli/init_commands.py
kuzu_memory/cli/install_commands_simple.py
kuzu_memory/cli/install_unified.py
kuzu_memory/cli/mcp_install_commands.py
kuzu_memory/cli/mcp_server_command.py
kuzu_memory/cli/memory_commands.py
kuzu_memory/cli/migrations_commands.py
kuzu_memory/cli/project_commands.py
kuzu_memory/cli/service_manager.py
kuzu_memory/cli/setup_commands.py
kuzu_memory/cli/status_commands.py
kuzu_memory/cli/update_commands.py
kuzu_memory/cli/_deprecated/__init__.py
kuzu_memory/cli/_deprecated/auggie_commands.py
kuzu_memory/cli/_deprecated/claude_commands.py
kuzu_memory/cli/_deprecated/diagnostic_commands.py
kuzu_memory/cli/_deprecated/install_commands.py
kuzu_memory/cli/_deprecated/mcp_commands.py
kuzu_memory/cli/_deprecated/utility_commands.py
kuzu_memory/connection_pool/__init__.py
kuzu_memory/connection_pool/kuzu_connection.py
kuzu_memory/connection_pool/kuzu_pool.py
kuzu_memory/core/__init__.py
kuzu_memory/core/config.py
kuzu_memory/core/constants.py
kuzu_memory/core/container.py
kuzu_memory/core/dependencies.py
kuzu_memory/core/internal_models.py
kuzu_memory/core/memory.py
kuzu_memory/core/models.py
kuzu_memory/core/prune.py
kuzu_memory/core/validators.py
kuzu_memory/extraction/__init__.py
kuzu_memory/extraction/entities.py
kuzu_memory/extraction/patterns.py
kuzu_memory-1.6.33.dist-info/METADATA
kuzu_memory-1.6.33.dist-info/WHEEL
kuzu_memory-1.6.33.dist-info/entry_points.txt
kuzu_memory-1.6.33.dist-info/top_level.txt
kuzu_memory-1.6.33.dist-info/RECORD
