Metadata-Version: 2.4
Name: kuzu-memory
Version: 1.6.33
Summary: Lightweight, embedded graph-based memory system for AI applications
Author-email: KuzuMemory Team <team@kuzu-memory.dev>
License: MIT
Project-URL: Homepage, https://github.com/kuzu-memory/kuzu-memory
Project-URL: Documentation, https://kuzu-memory.readthedocs.io
Project-URL: Repository, https://github.com/kuzu-memory/kuzu-memory
Project-URL: Issues, https://github.com/kuzu-memory/kuzu-memory/issues
Keywords: ai,memory,graph,database,kuzu,chatbot,llm
Classifier: Development Status :: 5 - Production/Stable
Classifier: Intended Audience :: Developers
Classifier: License :: OSI Approved :: MIT License
Classifier: Programming Language :: Python :: 3
Classifier: Programming Language :: Python :: 3.11
Classifier: Programming Language :: Python :: 3.12
Classifier: Topic :: Software Development :: Libraries :: Python Modules
Classifier: Topic :: Scientific/Engineering :: Artificial Intelligence
Requires-Python: >=3.11
Requires-Dist: kuzu>=0.4.0
Requires-Dist: pydantic>=2.0
Requires-Dist: click>=8.1.0
Requires-Dist: pyyaml>=6.0
Requires-Dist: python-dateutil>=2.8
Requires-Dist: typing-extensions>=4.5
Requires-Dist: rich>=13.0.0
Requires-Dist: psutil>=5.9.0
Requires-Dist: gitpython>=3.1.0
Requires-Dist: mcp>=1.0.0
Requires-Dist: packaging>=20.0
Requires-Dist: tomli-w>=1.0.0
Requires-Dist: py-mcp-installer>=0.1.5
Provides-Extra: nlp
Requires-Dist: nltk>=3.8; extra == "nlp"
Requires-Dist: scikit-learn>=1.3; extra == "nlp"
Requires-Dist: numpy>=1.24; extra == "nlp"
Provides-Extra: ner
Requires-Dist: spacy>=3.5; extra == "ner"
Provides-Extra: dev
Requires-Dist: pytest>=7.0; extra == "dev"
Requires-Dist: pytest-benchmark>=4.0; extra == "dev"
Requires-Dist: pytest-cov>=4.0; extra == "dev"
Requires-Dist: pytest-asyncio>=0.23.0; extra == "dev"
Requires-Dist: pytest-timeout>=2.2.0; extra == "dev"
Requires-Dist: pytest-mock>=3.10; extra == "dev"
Requires-Dist: black>=23.0; extra == "dev"
Requires-Dist: build>=0.10; extra == "dev"
Requires-Dist: isort>=5.12; extra == "dev"
Requires-Dist: ruff>=0.1.0; extra == "dev"
Requires-Dist: mypy>=1.0; extra == "dev"
Requires-Dist: pre-commit>=3.0; extra == "dev"
Requires-Dist: pytest-xdist>=3.0; extra == "dev"
Requires-Dist: towncrier>=23.11.0; extra == "dev"
Requires-Dist: twine>=4.0; extra == "dev"
Provides-Extra: test
Requires-Dist: pytest>=7.0; extra == "test"
Requires-Dist: pytest-benchmark>=4.0; extra == "test"
Requires-Dist: pytest-cov>=4.0; extra == "test"
Requires-Dist: pytest-asyncio>=0.23.0; extra == "test"
Requires-Dist: pytest-timeout>=2.2.0; extra == "test"
Requires-Dist: pytest-mock>=3.10; extra == "test"
